[{"name":["IT Laboratories"],"type":["University Library Lab"],"Description":["Eight rooms for individual work at the Communication Reading Room are equipped with computers with special software."],"link":["https://biblioteka.vu.lt/en/places/scic/it-laboratories"],"coordinates":{"lat":[54.682845144376756],"lon":[25.286736510860923]},"Institution":["Vilnius University Library"],"Contact email":["mb@mb.vu.lt"],"Activity calendar":[""],"Carpentries":["Yes/No"],"Software":[["AutoCAD"],["CS6 Adobe Design Std 6"], ["Matlab"], ["OriginPro"], ["SolidWorks"], ["Sony Vegas Movie Studio Platinum 12.0"], ["Sound Forge Audio Studio"], ["Sony DVD Architect Studio 5.0"],["etc"]],"Hardware":["Text"],"Techniques":[["Text"],["Text"],["etc"]],"Fields":[["Digital Humanities"],["etc"]],"Target audience":[["Students"],["Employees"]],"Collaborations":["Text"]}]